memex_client/__init__.py
memex_client/_version.py
memex_client/client.py
memex_client/errors.py
memex_client/scientist.py
memex_client/protos/__init__.py
memex_client/protos/brainiac_pb2.py
memex_client/protos/brainiac_pb2_grpc.py
memex_client/tests/__init__.py
memex_client/tests/third_party.py
memex_client-0.0.4.7rc0.dist-info/AUTHORS.rst
memex_client-0.0.4.7rc0.dist-info/LICENSE
memex_client-0.0.4.7rc0.dist-info/METADATA
memex_client-0.0.4.7rc0.dist-info/WHEEL
memex_client-0.0.4.7rc0.dist-info/top_level.txt
memex_client-0.0.4.7rc0.dist-info/RECORD
