Metadata-Version: 2.1
Name: memex-client
Version: 0.0.4.7rc0
Summary: The client library to make and use brainiac modules.
Home-page: https://github.com/suyogsoti/client-lib
Author: Suyog Soti
Author-email: suyog.soti@gmail.com
License: MIT
Platform: UNKNOWN
Classifier: Development Status :: 2 - Pre-Alpha
Classifier: Intended Audience :: Developers
Classifier: Natural Language :: English
Classifier: Programming Language :: Python :: 3.7
Requires-Dist: cloudpickle
Requires-Dist: grpcio
Requires-Dist: grpcio-tools
